{"is_source_file": true, "format": "Java", "description": "This file defines a marker interface named MockWarningDevice used for a fake warning device within the 'com.comcast.xh.zith.device' package.", "external_files": ["http://www.apache.org/licenses/LICENSE-2.0"], "external_methods": [], "published": ["MockWarningDevice"], "classes": [{"name": "MockWarningDevice", "description": "Marker interface for a fake warning device"}], "methods": [], "calls": [], "search-terms": ["MockWarningDevice", "marker interface", "fake warning device", "comcast xh zith device"], "state": 2, "file_id": 320, "knowledge_revision": 13481, "git_revision": "", "hash": "320a92574bfa0927b4d851abe7d0b27a", "format-version": 4, "code-base-name": "meta-rdk-sampleapp", "filename": "components/opensource/zilker-sdk/tools/zith/src/main/java/com/comcast/xh/zith/device/MockWarningDevice.java", "revision_history": [{"13481": ""}]}