{"is_source_file": true, "format": "C header file", "description": "This file defines interfaces related to 'trigger' functionality within the icrule component, including function declarations for freeing and parsing trigger data structures, along with include directives for dependencies.", "external_files": ["icrule/icrule.h", "libxml2/libxml/tree.h"], "external_methods": ["icrule_free_trigger", "icrule_parse_trigger_list"], "published": ["icrule_free_trigger", "icrule_parse_trigger_list"], "classes": [], "methods": [{"name": "icrule_free_trigger", "description": "Frees the memory allocated for a trigger object."}, {"name": "icrule_parse_trigger_list", "description": "Parses an XML node to populate a list of triggers."}], "calls": ["icrule_free_trigger", "icrule_parse_trigger_list"], "search-terms": ["trigger", "icrule", "libxml", "trigger list parser", "trigger free"], "state": 2, "file_id": 663, "knowledge_revision": 13821, "git_revision": "", "ctags": [{"_type": "tag", "name": "ZILKER_ICRULE_TRIGGER_H", "path": "/home/kavia/workspace/code-generation/Kirkstone/kirkstone/components/opensource/zilker-sdk/source/libs/libicrule/src/icrule_trigger.h", "pattern": "/^#define ZILKER_ICRULE_TRIGGER_H$/", "language": "C++", "kind": "macro"}], "hash": "b94f0bce9969c61b79e6a24a112623ef", "format-version": 4, "code-base-name": "meta-rdk-sampleapp", "filename": "components/opensource/zilker-sdk/source/libs/libicrule/src/icrule_trigger.h", "revision_history": [{"13821": ""}]}