{"is_source_file": false, "format": "", "description": "", "external_files": [], "external_methods": [], "published": [], "classes": [], "methods": [], "calls": [], "search-terms": [], "state": 2, "file_id": 13153, "knowledge_revision": 26042, "git_revision": "", "hash": "29970f808ecc99e68749f48869557dbc", "format-version": 4, "code-base-name": "meta-rdk-sampleapp", "filename": "meta-cmf-raspberrypi/meta-rdk-broadband/recipes-ccsp/ccsp/ccsp-cr/cr-deviceprofile_rpi.xml", "revision_history": [{"26042": ""}]}