{"is_source_file": true, "format": "C/C++ header file", "description": "This header file provides module-specific definitions and function declarations for Telemetry 2.0 component, including configuration file paths and initialization functions.", "external_files": ["msg_daemon.cfg", "/usr/ccsp/telemetry/T2Agent.cfg"], "external_methods": ["initTR181_dm", "unInitTR181_dm"], "published": ["MESSAGE_BUS_CONFIG_FILE", "CCSP_T2_START_CFG_FILE", "initTR181_dm", "unInitTR181_dm"], "classes": [], "methods": [{"name": "unInitTR181_dm", "description": "Uninitializes or cleans up the TR-181 Data Model for the Telemetry component."}], "calls": ["initTR181_dm", "unInitTR181_dm"], "search-terms": ["Telemetry 2.0", "t2_custom.h", "TR-181", "telemetry configuration", "message bus config"], "state": 2, "file_id": 12840, "knowledge_revision": 25737, "git_revision": "", "ctags": [{"_type": "tag", "name": "CCSP_T2_START_CFG_FILE", "path": "/home/kavia/workspace/code-generation/Kirkstone/kirkstone/rdk/components/generic/telemetry/source/t2ssp/t2_custom.h", "pattern": "/^#define CCSP_T2_START_CFG_FILE /", "language": "C++", "kind": "macro"}, {"_type": "tag", "name": "MESSAGE_BUS_CONFIG_FILE", "path": "/home/kavia/workspace/code-generation/Kirkstone/kirkstone/rdk/components/generic/telemetry/source/t2ssp/t2_custom.h", "pattern": "/^#define MESSAGE_BUS_CONFIG_FILE /", "language": "C++", "kind": "macro"}, {"_type": "tag", "name": "_T2_CUSTOM_H_", "path": "/home/kavia/workspace/code-generation/Kirkstone/kirkstone/rdk/components/generic/telemetry/source/t2ssp/t2_custom.h", "pattern": "/^#define  _T2_CUSTOM_H_$/", "language": "C++", "kind": "macro"}], "hash": "ec729ece0bc7d5e93d5a961973752b96", "format-version": 4, "code-base-name": "meta-rdk-sampleapp", "filename": "rdk/components/generic/telemetry/source/t2ssp/t2_custom.h", "revision_history": [{"25737": ""}]}