{"is_source_file": true, "file_id": 12660, "git_revision": "", "state": 1, "description": "", "external_files": [], "external_methods": [], "published": [], "classes": [], "methods": [], "calls": [], "search-terms": [], "ctags": [{"_type": "tag", "name": "rdk_logger_module_fetch", "path": "/home/kavia/workspace/code-generation/Kirkstone/kirkstone/rdk/components/generic/WebconfigFramework/source/webconfig_logging.c", "pattern": "/^const char *rdk_logger_module_fetch(void)$/", "language": "C", "typeref": "typename:const char *", "kind": "function", "signature": "(void)"}, {"_type": "tag", "name": "wbTraceLogAPI", "path": "/home/kavia/workspace/code-generation/Kirkstone/kirkstone/rdk/components/generic/WebconfigFramework/source/webconfig_logging.c", "pattern": "/^void wbTraceLogAPI(const char *format, ...)$/", "language": "C", "typeref": "typename:void", "kind": "function", "signature": "(const char * format,...)"}], "format": "C", "hash": "618c9842961bf6b93187db77bed90454", "format-version": 4, "code-base-name": "meta-rdk-sampleapp", "filename": "rdk/components/generic/WebconfigFramework/source/webconfig_logging.c", "knowledge_revision": 12663}