{"is_source_file": true, "format": "C header file", "description": "This header file includes all the necessary header files required by the TLS Environment Controller implementation within a BroadWay Service Delivery System. It primarily contains include directives, licensing information, and module descriptions, with no implementation code or definitions of symbols, classes, or functions.", "external_files": ["ansc_platform.h", "ansc_crypto_interface.h", "ansc_crypto_external_api.h", "ansc_oco_interface.h", "ansc_oco_external_api.h", "ansc_tso_interface.h", "ansc_tso_external_api.h", "tls_co_oid.h", "tls_co_name.h", "tls_co_type.h", "tls_definitions.h", "tls_properties.h", "tls_eco_interface.h", "tls_eco_exported_api.h", "tls_eco_internal_api.h", "tls_smo_interface.h", "tls_smo_exported_api.h", "tls_cpo_interface.h", "tls_cpo_exported_api.h", "tls_cco_interface.h", "tls_cco_exported_api.h"], "external_methods": [], "published": [], "classes": [], "methods": [], "calls": [], "search-terms": ["tls_eco_global", "TlsEnvController", "TLS", "environment", "header includes", "TLS Env Controller"], "state": 2, "file_id": 10412, "knowledge_revision": 23398, "git_revision": "", "ctags": [{"_type": "tag", "name": "_TLS_ECO_GLOBAL_", "path": "/home/kavia/workspace/code-generation/Kirkstone/kirkstone/rdkb/components/opensource/ccsp/CcspCommonLibrary/source/util_api/tls/components/TlsEnvController/tls_eco_global.h", "pattern": "/^#define  _TLS_ECO_GLOBAL_$/", "language": "C++", "kind": "macro"}], "hash": "1b59276b9a9bef887553cc94bdfe685b", "format-version": 4, "code-base-name": "meta-rdk-sampleapp", "filename": "rdkb/components/opensource/ccsp/CcspCommonLibrary/source/util_api/tls/components/TlsEnvController/tls_eco_global.h", "revision_history": [{"23398": ""}]}