{"is_source_file": true, "format": "Shell script", "description": "This file is a shell script responsible for starting and stopping a network tunnel, likely an SSH tunnel. It manages network interface configurations, IP address retrieval, and initiates SSH connections based on device-specific parameters.", "external_files": ["/etc/include.properties", "/etc/device.properties", "/etc/waninfo.sh", "/lib/rdk/t2Shared_api.sh", "/lib/rdk/utils.sh", "/usr/bin/GetConfigFile"], "external_methods": ["getWanInterfaceName", "getWanMacInterfaceName", "getCMIPAddress", "t2CountNotify"], "published": [], "classes": [], "methods": [{"name": "usage", "description": "Displays usage information for the script commands (start/stop)."}, {"name": "ip_to_hex", "description": "Converts an IPv4 address to its hexadecimal representation."}], "calls": ["getWanInterfaceName", "getWanMacInterfaceName", "getCMIPAddress", "t2CountNotify", "/usr/bin/ssh", "GetConfigFile", "cat", "grep", "awk", "cut", "sed", "ifconfig", "tr", "sleep", "kill", "rm"], "search-terms": ["startTunnel.sh", "network tunnel script", "SSH tunnel", "WAN_INTERFACE", "CM_IP", "rundaemon", "device-specific interface", "t2Shared_api.sh", "utils.sh"], "state": 2, "file_id": 7101, "knowledge_revision": 20184, "git_revision": "", "hash": "50bdc0f11f51475a55f4ea756f56e857", "format-version": 4, "code-base-name": "meta-rdk-sampleapp", "filename": "rdkb/components/opensource/ccsp/sysint/startTunnel.sh", "revision_history": [{"20184": ""}]}