{"is_source_file": true, "format": "C", "description": "This file contains stub implementations for Wi-Fi hardware abstraction layer (HAL) functions, primarily returning success codes (RETURN_OK). It serves as a placeholder or dummy implementation for Wi-Fi operations such as scanning, connecting, disconnecting, and managing Wi-Fi interfaces and neighbors.", "external_files": ["wifi_hal_rdk_framework.h", "wifi_hal_ap.h", "wifi_hal_generic.h"], "external_methods": ["wifi_receivedMgmtFrame_callback", "wifi_scanResults_callback", "wifi_staConnectionStatus_callback"], "published": ["wifi_hal_purgeScanResult", "wifi_hal_disconnect", "wifi_chan_event_register", "wifi_getApInterworkingElement", "wifi_hal_connect", "wifi_hal_createVAP", "wifi_hal_findNetworks", "wifi_hal_get_default_keypassphrase", "wifi_hal_get_default_ssid", "wifi_hal_get_default_wps_pin", "wifi_hal_getHalCapability", "wifi_hal_getScanResults", "wifi_hal_init", "wifi_hal_kickAssociatedDevice", "wifi_hal_mgmt_frame_callbacks_register", "wifi_hal_post_init", "wifi_hal_pre_init", "wifi_hal_scanResults_callback_register", "wifi_hal_setApWpsButtonPush", "wifi_hal_setApWpsCancel", "wifi_hal_setRadioOperatingParameters", "wifi_hal_staConnectionStatus_callback_register", "wifi_hal_startScan", "wifi_hal_get_default_country_code", "wifi_hal_getRadioVapInfoMap", "wifi_hal_get_default_radius_key", "wifi_hal_setApWpsPin", "wifi_delApAclDevice", "wifi_addApAclDevice", "wifi_setApMacAddressControlMode", "wifi_delApAclDevices", "wifi_hal_set_neighbor_report", "wifi_hal_startNeighborScan", "wifi_hal_getNeighboringWiFiStatus", "wifi_hal_setBTMRequest", "wifi_hal_setRMBeaconRequest", "wifi_hal_setNeighborReports", "wifi_hal_configNeighborReports", "is_db_upgrade_required"], "classes": [], "methods": [{"name": "BOOL is_db_upgrade_required(CHAR * inactive_firmware)", "scope": "", "scopeKind": "", "description": "unavailable"}, {"name": "INT wifi_addApAclDevice(INT apIndex,CHAR * DeviceMacAddress)", "scope": "", "scopeKind": "", "description": "unavailable"}, {"name": "INT wifi_anqpSendResponse(UINT apIndex,mac_address_t sta,unsigned char token,wifi_anqp_node_t * head)", "scope": "", "scopeKind": "", "description": "unavailable"}, {"name": "INT wifi_chan_event_register(wifi_chan_event_CB_t event_cb)", "scope": "", "scopeKind": "", "description": "unavailable"}, {"name": "INT wifi_delApAclDevice(INT apIndex,CHAR * DeviceMacAddress)", "scope": "", "scopeKind": "", "description": "unavailable"}, {"name": "INT wifi_delApAclDevices(INT apINdex)", "scope": "", "scopeKind": "", "description": "unavailable"}, {"name": "INT wifi_getApInterworkingElement(INT apIndex,wifi_InterworkingElement_t * output_struct)", "scope": "", "scopeKind": "", "description": "unavailable"}, {"name": "INT wifi_hal_configNeighborReports(UINT apIndex,bool enable,bool auto_resp)", "scope": "", "scopeKind": "", "description": "unavailable"}, {"name": "INT wifi_hal_connect(INT ap_index,wifi_bss_info_t * bss)", "scope": "", "scopeKind": "", "description": "unavailable"}, {"name": "INT wifi_hal_createVAP(wifi_radio_index_t index,wifi_vap_info_map_t * map)", "scope": "", "scopeKind": "", "description": "unavailable"}, {"name": "INT wifi_hal_disconnect(INT apIndex)", "scope": "", "scopeKind": "", "description": "unavailable"}, {"name": "INT wifi_hal_findNetworks(INT ap_index,wifi_channel_t * channel,wifi_bss_info_t ** bss_array,UINT * num_bss)", "scope": "", "scopeKind": "", "description": "unavailable"}, {"name": "INT wifi_hal_getHalCapability(wifi_hal_capability_t * hal)", "scope": "", "scopeKind": "", "description": "unavailable"}, {"name": "INT wifi_hal_getNeighboringWiFiStatus(INT radioIndex,wifi_neighbor_ap2_t ** neighbor_ap_array,UINT * output_array_size)", "scope": "", "scopeKind": "", "description": "unavailable"}, {"name": "INT wifi_hal_getRadioTemperature(wifi_radio_index_t radioIndex,wifi_radioTemperature_t * radioPhyTemperature)", "scope": "", "scopeKind": "", "description": "unavailable"}, {"name": "INT wifi_hal_getRadioVapInfoMap(wifi_radio_index_t index,wifi_vap_info_map_t * map)", "scope": "", "scopeKind": "", "description": "unavailable"}, {"name": "INT wifi_hal_getScanResults(wifi_radio_index_t index,wifi_channel_t * channel,wifi_bss_info_t ** bss,UINT * num_bss)", "scope": "", "scopeKind": "", "description": "unavailable"}, {"name": "INT wifi_hal_get_default_country_code(char * code)", "scope": "", "scopeKind": "", "description": "unavailable"}, {"name": "INT wifi_hal_get_default_keypassphrase(char * password,int vap_index)", "scope": "", "scopeKind": "", "description": "unavailable"}, {"name": "INT wifi_hal_get_default_radius_key(char * radius_key)", "scope": "", "scopeKind": "", "description": "unavailable"}, {"name": "INT wifi_hal_get_default_ssid(char * ssid,int vap_index)", "scope": "", "scopeKind": "", "description": "unavailable"}, {"name": "INT wifi_hal_get_default_wps_pin(char * pin)", "scope": "", "scopeKind": "", "description": "unavailable"}, {"name": "INT wifi_hal_init()", "scope": "", "scopeKind": "", "description": "unavailable"}, {"name": "INT wifi_hal_kickAssociatedDevice(INT ap_index,mac_address_t mac)", "scope": "", "scopeKind": "", "description": "unavailable"}, {"name": "INT wifi_hal_mgmt_frame_callbacks_register(wifi_receivedMgmtFrame_callback func)", "scope": "", "scopeKind": "", "description": "unavailable"}, {"name": "INT wifi_hal_post_init()", "scope": "", "scopeKind": "", "description": "unavailable"}, {"name": "INT wifi_hal_pre_init()", "scope": "", "scopeKind": "", "description": "unavailable"}, {"name": "INT wifi_hal_purgeScanResult(INT apIndex,bssid_t bssid)", "scope": "", "scopeKind": "", "description": "unavailable"}, {"name": "void wifi_hal_scanResults_callback_register(wifi_scanResults_callback func)", "scope": "", "scopeKind": "", "description": "unavailable"}, {"name": "INT wifi_hal_setApWpsButtonPush(INT ap_index)", "scope": "", "scopeKind": "", "description": "unavailable"}, {"name": "INT wifi_hal_setApWpsCancel(INT ap_index)", "scope": "", "scopeKind": "", "description": "unavailable"}, {"name": "INT wifi_hal_setApWpsPin(INT ap_index,char * wps_pin)", "scope": "", "scopeKind": "", "description": "unavailable"}, {"name": "INT wifi_hal_setBTMRequest(UINT apIndex,mac_address_t peerMac,wifi_BTMRequest_t * request)", "scope": "", "scopeKind": "", "description": "unavailable"}, {"name": "INT wifi_hal_setNeighborReports(UINT apIndex,UINT numNeighborReports,wifi_NeighborReport_t * neighborReports)", "scope": "", "scopeKind": "", "description": "unavailable"}, {"name": "INT wifi_hal_setRMBeaconRequest(UINT apIndex,mac_address_t peer_mac,wifi_BeaconRequest_t * in_req,UCHAR * out_DialogToken)", "scope": "", "scopeKind": "", "description": "unavailable"}, {"name": "INT wifi_hal_setRadioOperatingParameters(wifi_radio_index_t index,wifi_radio_operationParam_t * operationParam)", "scope": "", "scopeKind": "", "description": "unavailable"}, {"name": "INT wifi_hal_set_neighbor_report(UINT apIndex,UINT numNeighborReports,mac_address_t mac)", "scope": "", "scopeKind": "", "description": "unavailable"}, {"name": "void wifi_hal_staConnectionStatus_callback_register(wifi_staConnectionStatus_callback func)", "scope": "", "scopeKind": "", "description": "unavailable"}, {"name": "INT wifi_hal_startNeighborScan(INT apIndex,wifi_neighborScanMode_t scan_mode,INT dwell_time,UINT chan_num,UINT * chan_list)", "scope": "", "scopeKind": "", "description": "unavailable"}, {"name": "INT wifi_hal_startScan(wifi_radio_index_t index,wifi_neighborScanMode_t scan_mode,INT dwell_time,UINT num,UINT * chan_list)", "scope": "", "scopeKind": "", "description": "unavailable"}, {"name": "INT wifi_setApMacAddressControlMode(INT apIndex,INT filterMode)", "scope": "", "scopeKind": "", "description": "unavailable"}], "calls": ["return RETURN_OK", "return 0", "return FALSE"], "search-terms": ["wifi_hal", "stub", "Wi-Fi", "HAL", "connection", "scan", "VAP", "neighbor", "WPS", "AP"], "state": 2, "file_id": 5953, "knowledge_revision": 19057, "git_revision": "", "ctags": [{"_type": "tag", "name": "RETURN_OK", "path": "/home/kavia/workspace/code-generation/Kirkstone/kirkstone/rdkb/components/opensource/ccsp/OneWifi/source/stubs/wifi_hal_stubs.c", "pattern": "/^#define RETURN_OK /", "file": true, "language": "C", "kind": "macro"}, {"_type": "tag", "name": "is_db_upgrade_required", "path": "/home/kavia/workspace/code-generation/Kirkstone/kirkstone/rdkb/components/opensource/ccsp/OneWifi/source/stubs/wifi_hal_stubs.c", "pattern": "/^BOOL is_db_upgrade_required( CHAR* inactive_firmware)$/", "language": "C", "typeref": "typename:BOOL", "kind": "function", "signature": "(CHAR * inactive_firmware)"}, {"_type": "tag", "name": "wifi_addApAclDevice", "path": "/home/kavia/workspace/code-generation/Kirkstone/kirkstone/rdkb/components/opensource/ccsp/OneWifi/source/stubs/wifi_hal_stubs.c", "pattern": "/^INT wifi_addApAclDevice(INT apIndex, CHAR *DeviceMacAddress)$/", "language": "C", "typeref": "typename:INT", "kind": "function", "signature": "(INT apIndex,CHAR * DeviceMacAddress)"}, {"_type": "tag", "name": "wifi_anqpSendResponse", "path": "/home/kavia/workspace/code-generation/Kirkstone/kirkstone/rdkb/components/opensource/ccsp/OneWifi/source/stubs/wifi_hal_stubs.c", "pattern": "/^INT wifi_anqpSendResponse(UINT apIndex, mac_address_t sta, unsigned char token, wifi_anqp_node_t/", "language": "C", "typeref": "typename:INT", "kind": "function", "signature": "(UINT apIndex,mac_address_t sta,unsigned char token,wifi_anqp_node_t * head)"}, {"_type": "tag", "name": "wifi_chan_event_register", "path": "/home/kavia/workspace/code-generation/Kirkstone/kirkstone/rdkb/components/opensource/ccsp/OneWifi/source/stubs/wifi_hal_stubs.c", "pattern": "/^INT wifi_chan_event_register(wifi_chan_event_CB_t event_cb)$/", "language": "C", "typeref": "typename:INT", "kind": "function", "signature": "(wifi_chan_event_CB_t event_cb)"}, {"_type": "tag", "name": "wifi_delApAclDevice", "path": "/home/kavia/workspace/code-generation/Kirkstone/kirkstone/rdkb/components/opensource/ccsp/OneWifi/source/stubs/wifi_hal_stubs.c", "pattern": "/^INT wifi_delApAclDevice(INT apIndex, CHAR *DeviceMacAddress)$/", "language": "C", "typeref": "typename:INT", "kind": "function", "signature": "(INT apIndex,CHAR * DeviceMacAddress)"}, {"_type": "tag", "name": "wifi_delApAclDevices", "path": "/home/kavia/workspace/code-generation/Kirkstone/kirkstone/rdkb/components/opensource/ccsp/OneWifi/source/stubs/wifi_hal_stubs.c", "pattern": "/^INT wifi_delApAclDevices(INT apINdex)$/", "language": "C", "typeref": "typename:INT", "kind": "function", "signature": "(INT apINdex)"}, {"_type": "tag", "name": "wifi_getApInterworkingElement", "path": "/home/kavia/workspace/code-generation/Kirkstone/kirkstone/rdkb/components/opensource/ccsp/OneWifi/source/stubs/wifi_hal_stubs.c", "pattern": "/^INT wifi_getApInterworkingElement(INT apIndex, wifi_InterworkingElement_t *output_struct)$/", "language": "C", "typeref": "typename:INT", "kind": "function", "signature": "(INT apIndex,wifi_InterworkingElement_t * output_struct)"}, {"_type": "tag", "name": "wifi_hal_configNeighborReports", "path": "/home/kavia/workspace/code-generation/Kirkstone/kirkstone/rdkb/components/opensource/ccsp/OneWifi/source/stubs/wifi_hal_stubs.c", "pattern": "/^INT wifi_hal_configNeighborReports(UINT apIndex, bool enable, bool auto_resp)$/", "language": "C", "typeref": "typename:INT", "kind": "function", "signature": "(UINT apIndex,bool enable,bool auto_resp)"}, {"_type": "tag", "name": "wifi_hal_connect", "path": "/home/kavia/workspace/code-generation/Kirkstone/kirkstone/rdkb/components/opensource/ccsp/OneWifi/source/stubs/wifi_hal_stubs.c", "pattern": "/^INT wifi_hal_connect(INT ap_index, wifi_bss_info_t *bss)$/", "language": "C", "typeref": "typename:INT", "kind": "function", "signature": "(INT ap_index,wifi_bss_info_t * bss)"}, {"_type": "tag", "name": "wifi_hal_createVAP", "path": "/home/kavia/workspace/code-generation/Kirkstone/kirkstone/rdkb/components/opensource/ccsp/OneWifi/source/stubs/wifi_hal_stubs.c", "pattern": "/^INT wifi_hal_createVAP(wifi_radio_index_t index, wifi_vap_info_map_t *map)$/", "language": "C", "typeref": "typename:INT", "kind": "function", "signature": "(wifi_radio_index_t index,wifi_vap_info_map_t * map)"}, {"_type": "tag", "name": "wifi_hal_disconnect", "path": "/home/kavia/workspace/code-generation/Kirkstone/kirkstone/rdkb/components/opensource/ccsp/OneWifi/source/stubs/wifi_hal_stubs.c", "pattern": "/^INT wifi_hal_disconnect(INT apIndex)$/", "language": "C", "typeref": "typename:INT", "kind": "function", "signature": "(INT apIndex)"}, {"_type": "tag", "name": "wifi_hal_findNetworks", "path": "/home/kavia/workspace/code-generation/Kirkstone/kirkstone/rdkb/components/opensource/ccsp/OneWifi/source/stubs/wifi_hal_stubs.c", "pattern": "/^INT wifi_hal_findNetworks(INT ap_index, wifi_channel_t *channel, wifi_bss_info_t **bss_array, UI/", "language": "C", "typeref": "typename:INT", "kind": "function", "signature": "(INT ap_index,wifi_channel_t * channel,wifi_bss_info_t ** bss_array,UINT * num_bss)"}, {"_type": "tag", "name": "wifi_hal_getHalCapability", "path": "/home/kavia/workspace/code-generation/Kirkstone/kirkstone/rdkb/components/opensource/ccsp/OneWifi/source/stubs/wifi_hal_stubs.c", "pattern": "/^INT wifi_hal_getHalCapability(wifi_hal_capability_t *hal)$/", "language": "C", "typeref": "typename:INT", "kind": "function", "signature": "(wifi_hal_capability_t * hal)"}, {"_type": "tag", "name": "wifi_hal_getNeighboringWiFiStatus", "path": "/home/kavia/workspace/code-generation/Kirkstone/kirkstone/rdkb/components/opensource/ccsp/OneWifi/source/stubs/wifi_hal_stubs.c", "pattern": "/^INT wifi_hal_getNeighboringWiFiStatus(INT radioIndex, wifi_neighbor_ap2_t **neighbor_ap_array,$/", "language": "C", "typeref": "typename:INT", "kind": "function", "signature": "(INT radioIndex,wifi_neighbor_ap2_t ** neighbor_ap_array,UINT * output_array_size)"}, {"_type": "tag", "name": "wifi_hal_getRadioTemperature", "path": "/home/kavia/workspace/code-generation/Kirkstone/kirkstone/rdkb/components/opensource/ccsp/OneWifi/source/stubs/wifi_hal_stubs.c", "pattern": "/^INT wifi_hal_getRadioTemperature(wifi_radio_index_t radioIndex, wifi_radioTemperature_t *radioPh/", "language": "C", "typeref": "typename:INT", "kind": "function", "signature": "(wifi_radio_index_t radioIndex,wifi_radioTemperature_t * radioPhyTemperature)"}, {"_type": "tag", "name": "wifi_hal_getRadioVapInfoMap", "path": "/home/kavia/workspace/code-generation/Kirkstone/kirkstone/rdkb/components/opensource/ccsp/OneWifi/source/stubs/wifi_hal_stubs.c", "pattern": "/^INT wifi_hal_getRadioVapInfoMap(wifi_radio_index_t index, wifi_vap_info_map_t *map)$/", "language": "C", "typeref": "typename:INT", "kind": "function", "signature": "(wifi_radio_index_t index,wifi_vap_info_map_t * map)"}, {"_type": "tag", "name": "wifi_hal_getScanResults", "path": "/home/kavia/workspace/code-generation/Kirkstone/kirkstone/rdkb/components/opensource/ccsp/OneWifi/source/stubs/wifi_hal_stubs.c", "pattern": "/^INT wifi_hal_getScanResults(wifi_radio_index_t index, wifi_channel_t *channel, wifi_bss_info_t */", "language": "C", "typeref": "typename:INT", "kind": "function", "signature": "(wifi_radio_index_t index,wifi_channel_t * channel,wifi_bss_info_t ** bss,UINT * num_bss)"}, {"_type": "tag", "name": "wifi_hal_get_default_country_code", "path": "/home/kavia/workspace/code-generation/Kirkstone/kirkstone/rdkb/components/opensource/ccsp/OneWifi/source/stubs/wifi_hal_stubs.c", "pattern": "/^INT wifi_hal_get_default_country_code(char *code)$/", "language": "C", "typeref": "typename:INT", "kind": "function", "signature": "(char * code)"}, {"_type": "tag", "name": "wifi_hal_get_default_keypassphrase", "path": "/home/kavia/workspace/code-generation/Kirkstone/kirkstone/rdkb/components/opensource/ccsp/OneWifi/source/stubs/wifi_hal_stubs.c", "pattern": "/^INT wifi_hal_get_default_keypassphrase(char *password, int vap_index)$/", "language": "C", "typeref": "typename:INT", "kind": "function", "signature": "(char * password,int vap_index)"}, {"_type": "tag", "name": "wifi_hal_get_default_radius_key", "path": "/home/kavia/workspace/code-generation/Kirkstone/kirkstone/rdkb/components/opensource/ccsp/OneWifi/source/stubs/wifi_hal_stubs.c", "pattern": "/^INT wifi_hal_get_default_radius_key(char *radius_key)$/", "language": "C", "typeref": "typename:INT", "kind": "function", "signature": "(char * radius_key)"}, {"_type": "tag", "name": "wifi_hal_get_default_ssid", "path": "/home/kavia/workspace/code-generation/Kirkstone/kirkstone/rdkb/components/opensource/ccsp/OneWifi/source/stubs/wifi_hal_stubs.c", "pattern": "/^INT wifi_hal_get_default_ssid(char *ssid, int vap_index)$/", "language": "C", "typeref": "typename:INT", "kind": "function", "signature": "(char * ssid,int vap_index)"}, {"_type": "tag", "name": "wifi_hal_get_default_wps_pin", "path": "/home/kavia/workspace/code-generation/Kirkstone/kirkstone/rdkb/components/opensource/ccsp/OneWifi/source/stubs/wifi_hal_stubs.c", "pattern": "/^INT wifi_hal_get_default_wps_pin(char *pin)$/", "language": "C", "typeref": "typename:INT", "kind": "function", "signature": "(char * pin)"}, {"_type": "tag", "name": "wifi_hal_init", "path": "/home/kavia/workspace/code-generation/Kirkstone/kirkstone/rdkb/components/opensource/ccsp/OneWifi/source/stubs/wifi_hal_stubs.c", "pattern": "/^INT wifi_hal_init()$/", "language": "C", "typeref": "typename:INT", "kind": "function", "signature": "()"}, {"_type": "tag", "name": "wifi_hal_kickAssociatedDevice", "path": "/home/kavia/workspace/code-generation/Kirkstone/kirkstone/rdkb/components/opensource/ccsp/OneWifi/source/stubs/wifi_hal_stubs.c", "pattern": "/^INT wifi_hal_kickAssociatedDevice(INT ap_index, mac_address_t mac)$/", "language": "C", "typeref": "typename:INT", "kind": "function", "signature": "(INT ap_index,mac_address_t mac)"}, {"_type": "tag", "name": "wifi_hal_mgmt_frame_callbacks_register", "path": "/home/kavia/workspace/code-generation/Kirkstone/kirkstone/rdkb/components/opensource/ccsp/OneWifi/source/stubs/wifi_hal_stubs.c", "pattern": "/^INT wifi_hal_mgmt_frame_callbacks_register(wifi_receivedMgmtFrame_callback func)$/", "language": "C", "typeref": "typename:INT", "kind": "function", "signature": "(wifi_receivedMgmtFrame_callback func)"}, {"_type": "tag", "name": "wifi_hal_post_init", "path": "/home/kavia/workspace/code-generation/Kirkstone/kirkstone/rdkb/components/opensource/ccsp/OneWifi/source/stubs/wifi_hal_stubs.c", "pattern": "/^INT wifi_hal_post_init()$/", "language": "C", "typeref": "typename:INT", "kind": "function", "signature": "()"}, {"_type": "tag", "name": "wifi_hal_pre_init", "path": "/home/kavia/workspace/code-generation/Kirkstone/kirkstone/rdkb/components/opensource/ccsp/OneWifi/source/stubs/wifi_hal_stubs.c", "pattern": "/^INT wifi_hal_pre_init()$/", "language": "C", "typeref": "typename:INT", "kind": "function", "signature": "()"}, {"_type": "tag", "name": "wifi_hal_purgeScanResult", "path": "/home/kavia/workspace/code-generation/Kirkstone/kirkstone/rdkb/components/opensource/ccsp/OneWifi/source/stubs/wifi_hal_stubs.c", "pattern": "/^INT wifi_hal_purgeScanResult(INT apIndex, bssid_t bssid)$/", "language": "C", "typeref": "typename:INT", "kind": "function", "signature": "(INT apIndex,bssid_t bssid)"}, {"_type": "tag", "name": "wifi_hal_scanResults_callback_register", "path": "/home/kavia/workspace/code-generation/Kirkstone/kirkstone/rdkb/components/opensource/ccsp/OneWifi/source/stubs/wifi_hal_stubs.c", "pattern": "/^void wifi_hal_scanResults_callback_register(wifi_scanResults_callback func)$/", "language": "C", "typeref": "typename:void", "kind": "function", "signature": "(wifi_scanResults_callback func)"}, {"_type": "tag", "name": "wifi_hal_setApWpsButtonPush", "path": "/home/kavia/workspace/code-generation/Kirkstone/kirkstone/rdkb/components/opensource/ccsp/OneWifi/source/stubs/wifi_hal_stubs.c", "pattern": "/^INT wifi_hal_setApWpsButtonPush(INT ap_index)$/", "language": "C", "typeref": "typename:INT", "kind": "function", "signature": "(INT ap_index)"}, {"_type": "tag", "name": "wifi_hal_setApWpsCancel", "path": "/home/kavia/workspace/code-generation/Kirkstone/kirkstone/rdkb/components/opensource/ccsp/OneWifi/source/stubs/wifi_hal_stubs.c", "pattern": "/^INT wifi_hal_setApWpsCancel(INT ap_index)$/", "language": "C", "typeref": "typename:INT", "kind": "function", "signature": "(INT ap_index)"}, {"_type": "tag", "name": "wifi_hal_setApWpsPin", "path": "/home/kavia/workspace/code-generation/Kirkstone/kirkstone/rdkb/components/opensource/ccsp/OneWifi/source/stubs/wifi_hal_stubs.c", "pattern": "/^INT wifi_hal_setApWpsPin(INT ap_index, char *wps_pin)$/", "language": "C", "typeref": "typename:INT", "kind": "function", "signature": "(INT ap_index,char * wps_pin)"}, {"_type": "tag", "name": "wifi_hal_setBTMRequest", "path": "/home/kavia/workspace/code-generation/Kirkstone/kirkstone/rdkb/components/opensource/ccsp/OneWifi/source/stubs/wifi_hal_stubs.c", "pattern": "/^INT wifi_hal_setBTMRequest(UINT apIndex, mac_address_t peerMac, wifi_BTMRequest_t *request)$/", "language": "C", "typeref": "typename:INT", "kind": "function", "signature": "(UINT apIndex,mac_address_t peerMac,wifi_BTMRequest_t * request)"}, {"_type": "tag", "name": "wifi_hal_setNeighborReports", "path": "/home/kavia/workspace/code-generation/Kirkstone/kirkstone/rdkb/components/opensource/ccsp/OneWifi/source/stubs/wifi_hal_stubs.c", "pattern": "/^INT wifi_hal_setNeighborReports(UINT apIndex, UINT numNeighborReports,$/", "language": "C", "typeref": "typename:INT", "kind": "function", "signature": "(UINT apIndex,UINT numNeighborReports,wifi_NeighborReport_t * neighborReports)"}, {"_type": "tag", "name": "wifi_hal_setRMBeaconRequest", "path": "/home/kavia/workspace/code-generation/Kirkstone/kirkstone/rdkb/components/opensource/ccsp/OneWifi/source/stubs/wifi_hal_stubs.c", "pattern": "/^INT wifi_hal_setRMBeaconRequest(UINT apIndex, mac_address_t peer_mac, wifi_BeaconRequest_t *in_r/", "language": "C", "typeref": "typename:INT", "kind": "function", "signature": "(UINT apIndex,mac_address_t peer_mac,wifi_BeaconRequest_t * in_req,UCHAR * out_DialogToken)"}, {"_type": "tag", "name": "wifi_hal_setRadioOperatingParameters", "path": "/home/kavia/workspace/code-generation/Kirkstone/kirkstone/rdkb/components/opensource/ccsp/OneWifi/source/stubs/wifi_hal_stubs.c", "pattern": "/^INT wifi_hal_setRadioOperatingParameters(wifi_radio_index_t index, wifi_radio_operationParam_t */", "language": "C", "typeref": "typename:INT", "kind": "function", "signature": "(wifi_radio_index_t index,wifi_radio_operationParam_t * operationParam)"}, {"_type": "tag", "name": "wifi_hal_set_neighbor_report", "path": "/home/kavia/workspace/code-generation/Kirkstone/kirkstone/rdkb/components/opensource/ccsp/OneWifi/source/stubs/wifi_hal_stubs.c", "pattern": "/^INT wifi_hal_set_neighbor_report(UINT apIndex,UINT numNeighborReports, mac_address_t mac)$/", "language": "C", "typeref": "typename:INT", "kind": "function", "signature": "(UINT apIndex,UINT numNeighborReports,mac_address_t mac)"}, {"_type": "tag", "name": "wifi_hal_staConnectionStatus_callback_register", "path": "/home/kavia/workspace/code-generation/Kirkstone/kirkstone/rdkb/components/opensource/ccsp/OneWifi/source/stubs/wifi_hal_stubs.c", "pattern": "/^void wifi_hal_staConnectionStatus_callback_register(wifi_staConnectionStatus_callback func)$/", "language": "C", "typeref": "typename:void", "kind": "function", "signature": "(wifi_staConnectionStatus_callback func)"}, {"_type": "tag", "name": "wifi_hal_startNeighborScan", "path": "/home/kavia/workspace/code-generation/Kirkstone/kirkstone/rdkb/components/opensource/ccsp/OneWifi/source/stubs/wifi_hal_stubs.c", "pattern": "/^INT wifi_hal_startNeighborScan(INT apIndex, wifi_neighborScanMode_t scan_mode, INT dwell_time,$/", "language": "C", "typeref": "typename:INT", "kind": "function", "signature": "(INT apIndex,wifi_neighborScanMode_t scan_mode,INT dwell_time,UINT chan_num,UINT * chan_list)"}, {"_type": "tag", "name": "wifi_hal_startScan", "path": "/home/kavia/workspace/code-generation/Kirkstone/kirkstone/rdkb/components/opensource/ccsp/OneWifi/source/stubs/wifi_hal_stubs.c", "pattern": "/^INT wifi_hal_startScan(wifi_radio_index_t index, wifi_neighborScanMode_t scan_mode, INT dwell_ti/", "language": "C", "typeref": "typename:INT", "kind": "function", "signature": "(wifi_radio_index_t index,wifi_neighborScanMode_t scan_mode,INT dwell_time,UINT num,UINT * chan_list)"}, {"_type": "tag", "name": "wifi_setApMacAddressControlMode", "path": "/home/kavia/workspace/code-generation/Kirkstone/kirkstone/rdkb/components/opensource/ccsp/OneWifi/source/stubs/wifi_hal_stubs.c", "pattern": "/^INT wifi_setApMacAddressControlMode(INT apIndex, INT filterMode)$/", "language": "C", "typeref": "typename:INT", "kind": "function", "signature": "(INT apIndex,INT filterMode)"}], "hash": "cc15836256b155da22d27fecbccb4a6d", "format-version": 4, "code-base-name": "meta-rdk-sampleapp", "filename": "rdkb/components/opensource/ccsp/OneWifi/source/stubs/wifi_hal_stubs.c", "revision_history": [{"19057": ""}]}