{"is_source_file": true, "format": "PHP", "description": "This file is a PHP source script for configuring WAN settings and managing additional subnet entries in a network gateway device. It includes PHP logic for fetching current configuration, HTML for user interface, and JavaScript for client-side interactions and AJAX calls.", "external_files": ["includes/header.php", "includes/userbar.php", "includes/nav.php", "includes/utility.php"], "external_methods": ["getStr()", "fetchAdditionalSubnetTable()", "jAlert()", "jConfirm()", "jProgress()", "jHide()"], "published": ["getStr", "fetchAdditionalSubnetTable"], "classes": [], "methods": [], "calls": ["getStr()", "fetchAdditionalSubnetTable()", "jAlert()", "jConfirm()", "jProgress()", "jHide()"], "search-terms": ["WAN configuration", "PHP network setup", "subnet management", "ajaxSet_WAN_configuration", "ajaxSet_WAN_additional_subnet"], "state": 2, "file_id": 8781, "knowledge_revision": 21807, "git_revision": "", "hash": "48742d9533a9eb5e3f87d1e83477b110", "format-version": 4, "code-base-name": "meta-rdk-sampleapp", "filename": "rdkb/components/opensource/ccsp/webui-bwg/source/Styles/xb3/code/wan.php", "revision_history": [{"21807": ""}]}