{"is_source_file": true, "format": "PHP", "description": "This PHP script handles updating or editing blocked sites or keywords within a parental control system. It processes incoming POST data, performs validation, checks for conflicts with existing rules, and updates configuration via external functions.", "external_files": ["../includes/utility.php", "../includes/actionHandlerUtility.php"], "external_methods": ["getStr", "validId_PC", "validURL", "is_allowed_string", "isValInArray", "validTime", "validDays", "getParaValues", "days_time_conversion_get", "time_date_conflict", "DmExtSetStrsWithRootObj", "delTblObj", "addTblObj", "getInstanceIDs"], "published": [], "classes": [], "methods": [], "calls": ["getStr", "validId_PC", "validURL", "is_allowed_string", "isValInArray", "validTime", "validDays", "getParaValues", "days_time_conversion_get", "time_date_conflict", "DmExtSetStrsWithRootObj", "delTblObj", "addTblObj", "getInstanceIDs", "json_decode", "echo"], "search-terms": ["ajaxSet_edit_blockedSite.php", "ParentalControl", "BlockedSite", "manageEnabled", "InstanceID", "conflict", "URL", "Keyword", "time_conflict", "validation", "setStrs", "updateRules"], "state": 2, "file_id": 8797, "knowledge_revision": 21821, "git_revision": "", "hash": "1a0b79f22a59e7a050d3f08f81289f17", "format-version": 4, "code-base-name": "meta-rdk-sampleapp", "filename": "rdkb/components/opensource/ccsp/webui-bwg/source/Styles/xb3/code/actionHandler/ajaxSet_edit_blockedSite.php", "revision_history": [{"21821": ""}]}