{"is_source_file": true, "format": "C header file", "description": "This file declares external API functions related to the Ansc Ato Protocol Object, including creation, removal, enrollment, and initialization functions.", "external_files": [], "external_methods": [], "published": ["AnscCreateAtoProto", "AnscAtoProtoCreate", "AnscAtoProtoRemove", "AnscAtoProtoEnrollObjects", "AnscAtoProtoInitialize"], "classes": [], "methods": [{"name": "AnscCreateAtoProto", "description": "Creates and returns a handle to a new Ato Protocol Object, given container, owner, and reserved handles."}, {"name": "AnscAtoProtoCreate", "description": "Creates a new Ato Protocol Object instance with specified context and owner handles."}, {"name": "AnscAtoProtoRemove", "description": "Removes and cleans up the specified Ato Protocol Object instance."}, {"name": "AnscAtoProtoEnrollObjects", "description": "Enrolls necessary objects into the Ato Protocol Object instance."}, {"name": "AnscAtoProtoInitialize", "description": "Initializes the Ato Protocol Object instance."}], "calls": [], "search-terms": ["AtoProtocol", "ANSC_HANDLE", "AnscCreateAtoProto", "AnscAtoProtoRemove", "AnscAtoProtoInitialize", "header", "external API"], "state": 2, "file_id": 11937, "knowledge_revision": 24851, "git_revision": "", "ctags": [{"_type": "tag", "name": "_ANSC_ATOPROTO_EXPORTED_API_", "path": "/home/kavia/workspace/code-generation/Kirkstone/kirkstone/rdkb/components/opensource/ccsp/CcspCommonLibrary/source/cosa/include/ansc_atoproto_external_api.h", "pattern": "/^#define  _ANSC_ATOPROTO_EXPORTED_API_$/", "language": "C++", "kind": "macro"}], "hash": "f95fe448a3ebec2f55e8ea97e175245d", "format-version": 4, "code-base-name": "meta-rdk-sampleapp", "filename": "rdkb/components/opensource/ccsp/CcspCommonLibrary/source/cosa/include/ansc_atoproto_external_api.h", "revision_history": [{"24851": ""}]}