{"is_source_file": false, "format": "", "description": "", "external_files": [], "external_methods": [], "published": [], "classes": [], "methods": [], "calls": [], "search-terms": [], "state": 2, "file_id": 7606, "knowledge_revision": 20673, "git_revision": "", "hash": "c2dc3458a085c2638b1da78c096c57f3", "format-version": 4, "code-base-name": "meta-rdk-sampleapp", "filename": "rdkb/components/opensource/ccsp/Utopia/source/scripts/init/service.d/ddns_daily.sh", "revision_history": [{"20673": ""}]}