{"is_source_file": false, "format": "", "description": "", "external_files": [], "external_methods": [], "published": [], "classes": [], "methods": [], "calls": [], "search-terms": [], "state": 2, "file_id": 6736, "knowledge_revision": 19825, "git_revision": "", "hash": "5950305088870d53d5fc3d95f2f764e9", "format-version": 4, "code-base-name": "meta-rdk-sampleapp", "filename": "rdkb/components/opensource/ccsp/CcspSnmpPa/Mib2DmMapping/Ccsp_SA-RG-MIB-WanDns.xml", "revision_history": [{"19825": ""}]}