{"is_source_file": true, "format": "C header file", "description": "This file defines APIs and data structures for DNS diagnostics and NSLookup diagnostics in a C-based data model library. It includes function declarations for getting and setting diagnostic parameters, as well as managing diagnostic result entries.", "external_files": ["cosa_dns_dml.h", "Licenses.txt"], "external_methods": ["BOOL NSLookupDiagnostics_GetParamBoolValue", "BOOL NSLookupDiagnostics_SetParamBoolValue", "BOOL NSLookupDiagnostics_GetParamIntValue", "BOOL NSLookupDiagnostics_SetParamIntValue", "BOOL NSLookupDiagnostics_GetParamUlongValue", "BOOL NSLookupDiagnostics_SetParamUlongValue", "ULONG NSLookupDiagnostics_GetParamStringValue", "BOOL NSLookupDiagnostics_SetParamStringValue", "BOOL NSLookupDiagnostics_Validate", "ULONG NSLookupDiagnostics_Commit", "ULONG NSLookupDiagnostics_Rollback", "ULONG Result_GetEntryCount", "ANSC_HANDLE Result_GetEntry", "BOOL Result_IsUpdated", "ULONG Result_Synchronize", "BOOL Result_GetParamBoolValue", "BOOL Result_GetParamIntValue", "BOOL Result_GetParamUlongValue", "ULONG Result_GetParamStringValue"], "published": ["NSLookupDiagnostics_GetParamBoolValue", "NSLookupDiagnostics_SetParamBoolValue", "NSLookupDiagnostics_GetParamIntValue", "NSLookupDiagnostics_SetParamIntValue", "NSLookupDiagnostics_GetParamUlongValue", "NSLookupDiagnostics_SetParamUlongValue", "NSLookupDiagnostics_GetParamStringValue", "NSLookupDiagnostics_SetParamStringValue", "NSLookupDiagnostics_Validate", "NSLookupDiagnostics_Commit", "NSLookupDiagnostics_Rollback", "Result_GetEntryCount", "Result_GetEntry", "Result_IsUpdated", "Result_Synchronize", "Result_GetParamBoolValue", "Result_GetParamIntValue", "Result_GetParamUlongValue", "Result_GetParamStringValue"], "classes": [], "methods": [{"name": "NSLookupDiagnostics_GetParamBoolValue", "description": "Retrieves a boolean parameter value for the NSLookupDiagnostics object."}, {"name": "NSLookupDiagnostics_SetParamBoolValue", "description": "Sets a boolean parameter value for the NSLookupDiagnostics object."}, {"name": "NSLookupDiagnostics_GetParamIntValue", "description": "Retrieves an integer parameter value for the NSLookupDiagnostics object."}, {"name": "NSLookupDiagnostics_SetParamIntValue", "description": "Sets an integer parameter value for the NSLookupDiagnostics object."}, {"name": "NSLookupDiagnostics_GetParamUlongValue", "description": "Retrieves a ULONG parameter value for the NSLookupDiagnostics object."}, {"name": "NSLookupDiagnostics_SetParamUlongValue", "description": "Sets a ULONG parameter value for the NSLookupDiagnostics object."}, {"name": "NSLookupDiagnostics_GetParamStringValue", "description": "Retrieves a string parameter value for the NSLookupDiagnostics object."}, {"name": "NSLookupDiagnostics_SetParamStringValue", "description": "Sets a string parameter value for the NSLookupDiagnostics object."}, {"name": "NSLookupDiagnostics_Validate", "description": "Validates the parameters for NSLookupDiagnostics."}, {"name": "NSLookupDiagnostics_Commit", "description": "Commits changes to NSLookupDiagnostics parameters."}, {"name": "NSLookupDiagnostics_Rollback", "description": "Rolls back changes to NSLookupDiagnostics parameters."}, {"name": "Result_GetEntryCount", "description": "Returns the count of diagnostic result entries."}, {"name": "Result_GetEntry", "description": "Retrieves a specific diagnostic result entry by index."}, {"name": "Result_IsUpdated", "description": "Checks if the diagnostic results have been updated."}, {"name": "Result_Synchronize", "description": "Synchronizes the result entries with the current data."}, {"name": "Result_GetParamBoolValue", "description": "Retrieves a boolean value from a result entry."}, {"name": "Result_GetParamIntValue", "description": "Retrieves an integer value from a result entry."}, {"name": "Result_GetParamUlongValue", "description": "Retrieves a ULONG value from a result entry."}, {"name": "Result_GetParamStringValue", "description": "Retrieves a string value from a result entry."}], "search-terms": ["DNS Diagnostics", "NSLookup Diagnostics", "cosa_dns_dml.h", "DNS.Diagnostics.NSLookupDiagnostics", "Result Entries", "Data Model Library APIs"], "state": 2, "file_id": 9057, "knowledge_revision": 22084, "git_revision": "", "ctags": [{"_type": "tag", "name": "_COSA_DNS_DML_H", "path": "/home/kavia/workspace/code-generation/Kirkstone/kirkstone/rdkb/components/opensource/ccsp/TestAndDiagnostic/source/dmltad/cosa_dns_dml.h", "pattern": "/^#define  _COSA_DNS_DML_H$/", "language": "C++", "kind": "macro"}], "hash": "247d25962b491e27d3fa20672c0ff554", "format-version": 4, "code-base-name": "meta-rdk-sampleapp", "filename": "rdkb/components/opensource/ccsp/TestAndDiagnostic/source/dmltad/cosa_dns_dml.h", "revision_history": [{"22084": ""}]}