{"is_source_file": true, "format": "C header file", "description": "This header file declares functions and macros related to BLE HAL (Hardware Abstraction Layer) for a specific TDK BLE protocol. It includes function prototypes for getting BLE status and enabling BLE, as well as defining status codes.", "external_files": ["bt_hal.h"], "external_methods": ["BLE_Status_e"], "published": ["SSP_SUCCESS", "SSP_FAILURE", "ssp_BLEHAL_GetStatus", "ssp_BLEHAL_Enable"], "classes": [], "methods": [{"name": "ssp_BLEHAL_GetStatus", "description": "Retrieves the current BLE status, possibly with negative scenario handling."}, {"name": "ssp_BLEHAL_Enable", "description": "Enables BLE functionality based on the given status."}], "calls": ["ssp_BLEHAL_GetStatus", "ssp_BLEHAL_Enable"], "search-terms": ["BLE_HAL", "ssp_BLEHAL", "bt_hal", "SSP_SUCCESS", "SSP_FAILURE", "BLE_Status_e"], "state": 2, "file_id": 5603, "knowledge_revision": 18712, "git_revision": "", "ctags": [{"_type": "tag", "name": "SSP_FAILURE", "path": "/home/kavia/workspace/code-generation/Kirkstone/kirkstone/rdkb/tools/tdkb/tdkb_lib/include/ssp_tdk_blehal_wrp.h", "pattern": "/^#define SSP_FAILURE /", "language": "C++", "kind": "macro"}, {"_type": "tag", "name": "SSP_SUCCESS", "path": "/home/kavia/workspace/code-generation/Kirkstone/kirkstone/rdkb/tools/tdkb/tdkb_lib/include/ssp_tdk_blehal_wrp.h", "pattern": "/^#define SSP_SUCCESS /", "language": "C++", "kind": "macro"}, {"_type": "tag", "name": "__SSP_TDK_BLEHAL_WRP_H__", "path": "/home/kavia/workspace/code-generation/Kirkstone/kirkstone/rdkb/tools/tdkb/tdkb_lib/include/ssp_tdk_blehal_wrp.h", "pattern": "/^#define __SSP_TDK_BLEHAL_WRP_H__$/", "language": "C++", "kind": "macro"}], "hash": "84fad5f732b93ce7cc58392f6188b78c", "format-version": 4, "code-base-name": "meta-rdk-sampleapp", "filename": "rdkb/tools/tdkb/tdkb_lib/include/ssp_tdk_blehal_wrp.h", "revision_history": [{"18712": ""}]}