{"is_source_file": true, "format": "shell script", "description": "This file is a shell script that manages the download of certain binaries (socat and stunnel) for the ShortsDL feature, including checks for feature enablement, existing binaries, and download retries.", "external_files": ["/etc/utopia/service.d/log_capture_path.sh", "/fss/gw/etc/utopia/service.d/log_env_var.sh", "/etc/log_timestamp.sh", "/etc/rdm/downloadMgr.sh"], "external_methods": ["log_capture_path.sh: echo_t", "log_env_var.sh: syscfg", "log_timestamp.sh: echo_t"], "published": [], "classes": [], "methods": [{"name": "main", "description": "Main script logic that checks feature enablement, verifies presence of binaries, and performs downloads with retries."}], "calls": ["syscfg get ShortsDL", "echo_t", "sh /etc/rdm/downloadMgr.sh", "sleep 10", "exit"], "search-terms": ["ShortsDL", "downloadMgr.sh", "socat", "stunnel", "shortsDownload.sh", "download script", "feature check", "binary download"], "state": 2, "file_id": 7166, "knowledge_revision": 20244, "git_revision": "", "hash": "fc2663f29327a7bce230315b05531443", "format-version": 4, "code-base-name": "meta-rdk-sampleapp", "filename": "rdkb/components/opensource/ccsp/sysint/shortsDownload.sh", "revision_history": [{"20244": ""}]}