{"is_source_file": true, "format": "Shell script", "description": "This script initializes and manages the start of the 'parodus' process related to device health checks and configuration retrieval. It reads various device status parameters, constructs a command to start 'parodus' with appropriate arguments, and manages the process startup, including waiting for prerequisites.", "external_files": ["/tmp/parodusCmd.cmd", "/version.txt"], "external_methods": ["$GET", "cat", "grep", "tr", "cut", "ifconfig"], "published": [], "classes": [], "methods": [{"name": "main", "description": "Main script execution block that checks for existing command file, fetches device info, constructs the parodus command, and initiates the process."}], "calls": ["$GET", "cat", "grep", "tr", "cut", "ifconfig"], "search-terms": ["parodus_start.sh", "parodus", "device info", "health status", "bash script initialization", "device management"], "state": 2, "file_id": 8468, "knowledge_revision": 21498, "git_revision": "", "hash": "d3d7dc5cb2ac277d70fff493c234c554", "format-version": 4, "code-base-name": "meta-rdk-sampleapp", "filename": "rdkb/components/opensource/ccsp/CcspPandM/devices/scripts/Webpa/parodus_start.sh", "revision_history": [{"21498": ""}]}