{"is_source_file": true, "format": "PHP", "description": "This PHP script handles updating UPnP configuration settings via an AJAX request. It verifies user login, parses input JSON data, and updates device settings related to UPnP and zero-configuration handling.", "external_files": ["../includes/actionHandlerUtility.php"], "external_methods": ["setStr"], "published": [], "classes": [], "methods": [], "calls": ["setStr", "json_decode", "echo", "session_start", "isset", "exit"], "search-terms": ["UPnP", "ajaxSet_UPnP_configuration", "actionHandler", "zero-config", "session", "device settings"], "state": 2, "file_id": 8807, "knowledge_revision": 21833, "git_revision": "", "hash": "637632fd90a91682d3cb93d28398bac1", "format-version": 4, "code-base-name": "meta-rdk-sampleapp", "filename": "rdkb/components/opensource/ccsp/webui-bwg/source/Styles/xb3/code/actionHandler/ajaxSet_UPnP_configuration.php", "revision_history": [{"21833": ""}]}